servicenow_test_runner_scheduler/__init__.py
servicenow_test_runner_scheduler/cli.py
servicenow_test_runner_scheduler/config.py
servicenow_test_runner_scheduler/utils.py
servicenow_test_runner_scheduler-0.1.4.dist-info/entry_points.txt
servicenow_test_runner_scheduler-0.1.4.dist-info/LICENSE
servicenow_test_runner_scheduler-0.1.4.dist-info/WHEEL
servicenow_test_runner_scheduler-0.1.4.dist-info/METADATA
servicenow_test_runner_scheduler-0.1.4.dist-info/RECORD
