Metadata-Version: 2.1
Name: servicenow-test-runner-scheduler
Version: 0.1.4
Summary: ServiceNow - Start and Schedule Multiple ATF test runners in browser
Home-page: https://github.com/tddschn/servicenow-test-runner-scheduler
License: MIT
Keywords: servicenow,test,runner,scheduler
Author: Teddy Xinyuan Chen
Author-email: 45612704+tddschn@users.noreply.github.com
Requires-Python: >=3.10,<4.0
Classifier: License :: OSI Approved :: MIT License
Classifier: Programming Language :: Python :: 3
Classifier: Programming Language :: Python :: 3.10
Classifier: Topic :: Utilities
Requires-Dist: pydantic (>=1.9.1,<2.0.0)
Requires-Dist: python-dotenv (>=0.20.0,<0.21.0)
Requires-Dist: selenium (>=4.3.0,<5.0.0)
Project-URL: Bug Tracker, https://github.com/tddschn/servicenow-test-runner-scheduler/issues
Project-URL: Repository, https://github.com/tddschn/servicenow-test-runner-scheduler
